LICENSE
MANIFEST.in
README.rst
VERSION
marshmallow_sqlalchemy_referential.py
setup.cfg
setup.py
marshmallow_sqlalchemy_referential.egg-info/PKG-INFO
marshmallow_sqlalchemy_referential.egg-info/SOURCES.txt
marshmallow_sqlalchemy_referential.egg-info/dependency_links.txt
marshmallow_sqlalchemy_referential.egg-info/not-zip-safe
marshmallow_sqlalchemy_referential.egg-info/requires.txt
marshmallow_sqlalchemy_referential.egg-info/top_level.txt