Metadata-Version: 1.1
Name: marshmallow-sqlalchemy-referential
Version: 1.0.5
Summary: A marshmallow-sqlalchemy field allows referential CRUD on relational fields.
Home-page: https://github.com/twopicode/marshmallow-sqlalchemy-referential
Author: Nick Whyte
Author-email: nick@nickwhyte.com
License: UNKNOWN
Platform: UNKNOWN
Classifier: Intended Audience :: Developers
Classifier: Programming Language :: Python
